{
    "2020-02-09": [
        [
            {
                "time": "",
                "original_text": "【每周观点】关注疫情好转持续性，看好社服板块性行情！",
                "features": {
                    "keywords": [
                        "疫情好转",
                        "社服板块",
                        "板块性行情"
                    ],
                    "sentiment_score": 0.75,
                    "policy_related": "false",
                    "investment_strategy": "true",
                    "sector_focus": [
                        "社服"
                    ],
                    "causal_factor": "true",
                    "causal_impact": "positive",
                    "affected_by_time_series": "true",
                    "ts_effect_direction": "positive"
                }
            }
        ]
    ]
}