{
    "2020-08-25": [
        [
            {
                "time": "",
                "original_text": "又见券商股权无偿划转，这次是南京证券！60亿定增进度引关注",
                "features": {
                    "keywords": [
                        "券商股权",
                        "无偿划转",
                        "南京证券",
                        "60亿定增"
                    ],
                    "sentiment_score": 0.5,
                    "policy_related": "false",
                    "investment_strategy": "true",
                    "sector_focus": [
                        "金融",
                        "证券"
                    ],
                    "causal_factor": "true",
                    "causal_impact": "positive",
                    "affected_by_time_series": "true",
                    "ts_effect_direction": "positive"
                }
            }
        ]
    ]
}