{
    "2019-03-14": [
        [
            {
                "time": "2023-03-14",
                "original_text": "A股共发生51宗大宗交易成交18.15亿元（3月14日）",
                "features": {
                    "keywords": [
                        "A股",
                        "大宗交易",
                        "成交额"
                    ],
                    "sentiment_score": 0.6,
                    "policy_related": "false",
                    "investment_strategy": "false",
                    "sector_focus": [
                        "全市场"
                    ],
                    "causal_factor": "true",
                    "causal_impact": "positive",
                    "affected_by_time_series": "true",
                    "ts_effect_direction": "positive"
                }
            },
            {
                "time": "2023-03-14",
                "original_text": "正泰电器今日大宗交易成交731.58万股，成交价25.59元折价3.51%",
                "features": {
                    "keywords": [
                        "正泰电器",
                        "大宗交易",
                        "折价"
                    ],
                    "sentiment_score": -0.4,
                    "policy_related": "false",
                    "investment_strategy": "false",
                    "sector_focus": [
                        "电气设备"
                    ],
                    "causal_factor": "true",
                    "causal_impact": "negative",
                    "affected_by_time_series": "true",
                    "ts_effect_direction": "negative"
                }
            },
            {
                "time": "2023-03-14",
                "original_text": "深圳市市场监管局：3批次剩余电流动作断路器产品不合格 产品问题",
                "features": {
                    "keywords": [
                        "市场监管",
                        "断路器",
                        "不合格"
                    ],
                    "sentiment_score": -0.7,
                    "policy_related": "true",
                    "investment_strategy": "false",
                    "sector_focus": [
                        "电气设备"
                    ],
                    "causal_factor": "true",
                    "causal_impact": "negative",
                    "affected_by_time_series": "true",
                    "ts_effect_direction": "negative"
                }
            }
        ]
    ]
}