{
    "2021-04-27": [
        [
            {
                "time": "2021-Q1",
                "original_text": "领益智造：2021年第一季度净利润约4.63亿元，同比增长613.79%",
                "features": {
                    "keywords": [
                        "领益智造",
                        "净利润",
                        "同比增长",
                        "2021年第一季度"
                    ],
                    "sentiment_score": 0.9,
                    "policy_related": "false",
                    "investment_strategy": "false",
                    "sector_focus": [
                        "制造业",
                        "消费电子"
                    ],
                    "causal_factor": "true",
                    "causal_impact": "positive",
                    "affected_by_time_series": "true",
                    "ts_effect_direction": "positive"
                }
            },
            {
                "time": "2021-unknown",
                "original_text": "领益智造：公司拟对产业投资基金进行减资2.16亿元 减资破产",
                "features": {
                    "keywords": [
                        "领益智造",
                        "减资",
                        "产业投资基金",
                        "破产风险"
                    ],
                    "sentiment_score": -0.8,
                    "policy_related": "false",
                    "investment_strategy": "true",
                    "sector_focus": [
                        "制造业",
                        "投资"
                    ],
                    "causal_factor": "true",
                    "causal_impact": "negative",
                    "affected_by_time_series": "true",
                    "ts_effect_direction": "negative"
                }
            },
            {
                "time": "2021-Q1",
                "original_text": "领益智造：一季度净利润同比增长614%",
                "features": {
                    "keywords": [
                        "领益智造",
                        "净利润",
                        "同比增长",
                        "一季度"
                    ],
                    "sentiment_score": 0.9,
                    "policy_related": "false",
                    "investment_strategy": "false",
                    "sector_focus": [
                        "制造业",
                        "消费电子"
                    ],
                    "causal_factor": "true",
                    "causal_impact": "positive",
                    "affected_by_time_series": "true",
                    "ts_effect_direction": "positive"
                }
            },
            {
                "time": "2021-Q1",
                "original_text": "领益智造(002600.SZ)一季度净利润升613.79%至4.63亿元",
                "features": {
                    "keywords": [
                        "领益智造",
                        "净利润",
                        "同比增长",
                        "一季度"
                    ],
                    "sentiment_score": 0.9,
                    "policy_related": "false",
                    "investment_strategy": "false",
                    "sector_focus": [
                        "制造业",
                        "消费电子"
                    ],
                    "causal_factor": "true",
                    "causal_impact": "positive",
                    "affected_by_time_series": "true",
                    "ts_effect_direction": "positive"
                }
            },
            {
                "time": "2021-Q1",
                "original_text": "领益智造：一季度净利润同比增长613.79%",
                "features": {
                    "keywords": [
                        "领益智造",
                        "净利润",
                        "同比增长",
                        "一季度"
                    ],
                    "sentiment_score": 0.9,
                    "policy_related": "false",
                    "investment_strategy": "false",
                    "sector_focus": [
                        "制造业",
                        "消费电子"
                    ],
                    "causal_factor": "true",
                    "causal_impact": "positive",
                    "affected_by_time_series": "true",
                    "ts_effect_direction": "positive"
                }
            },
            {
                "time": "2021-afternoon",
                "original_text": "消费电子板块午后回暖，立讯精密跳涨3%",
                "features": {
                    "keywords": [
                        "消费电子",
                        "板块",
                        "午后回暖",
                        "立讯精密",
                        "跳涨"
                    ],
                    "sentiment_score": 0.7,
                    "policy_related": "false",
                    "investment_strategy": "false",
                    "sector_focus": [
                        "消费电子"
                    ],
                    "causal_factor": "false",
                    "causal_impact": "neutral",
                    "affected_by_time_series": "true",
                    "ts_effect_direction": "positive"
                }
            }
        ]
    ]
}