{
    "2019-06-27": [
        [
            {
                "time": "",
                "original_text": "华侨城拟10亿出售成都子公司51%股权 含洛带博客小镇等项目 资产异常",
                "features": {
                    "keywords": [
                        "华侨城",
                        "成都",
                        "子公司",
                        "股权出售",
                        "洛带博客小镇"
                    ],
                    "sentiment_score": -0.6,
                    "policy_related": "false",
                    "investment_strategy": "true",
                    "sector_focus": [
                        "房地产",
                        "旅游"
                    ],
                    "causal_factor": "true",
                    "causal_impact": "negative",
                    "affected_by_time_series": "false",
                    "ts_effect_direction": ""
                }
            },
            {
                "time": "",
                "original_text": "五大券商周五看好6板块27股",
                "features": {
                    "keywords": [
                        "券商",
                        "看好",
                        "板块",
                        "个股"
                    ],
                    "sentiment_score": 0.9,
                    "policy_related": "false",
                    "investment_strategy": "true",
                    "sector_focus": [
                        "金融"
                    ],
                    "causal_factor": "true",
                    "causal_impact": "positive",
                    "affected_by_time_series": "true",
                    "ts_effect_direction": "positive"
                }
            },
            {
                "time": "",
                "original_text": "华侨城拟转让成都地润51%股权 转让底价10.42亿元",
                "features": {
                    "keywords": [
                        "华侨城",
                        "成都",
                        "地润",
                        "股权转让",
                        "底价"
                    ],
                    "sentiment_score": -0.3,
                    "policy_related": "false",
                    "investment_strategy": "true",
                    "sector_focus": [
                        "房地产"
                    ],
                    "causal_factor": "true",
                    "causal_impact": "neutral",
                    "affected_by_time_series": "false",
                    "ts_effect_direction": ""
                }
            },
            {
                "time": "",
                "original_text": "【旅游】首旅与凯悦推出逸扉酒店 乌镇旅游再获政府补贴——餐饮旅游行业周报——看好（联系人：刘瑀，杨旭）",
                "features": {
                    "keywords": [
                        "首旅",
                        "凯悦",
                        "逸扉酒店",
                        "乌镇旅游",
                        "政府补贴"
                    ],
                    "sentiment_score": 0.8,
                    "policy_related": "true",
                    "investment_strategy": "true",
                    "sector_focus": [
                        "旅游",
                        "酒店"
                    ],
                    "causal_factor": "true",
                    "causal_impact": "positive",
                    "affected_by_time_series": "true",
                    "ts_effect_direction": "positive"
                }
            }
        ]
    ]
}