{
    "2018-11-07": [
        [
            {
                "time": "2018-11-08",
                "original_text": "California Water Service Group Holding (CWT) Ex-Dividend Date Scheduled for November 08, 2018",
                "features": {
                    "keywords": [
                        "CWT",
                        "Ex-Dividend",
                        "Scheduled"
                    ],
                    "sentiment_score": 0.5,
                    "policy_related": "false",
                    "investment_strategy": "true",
                    "sector_focus": [
                        "utilities",
                        "water"
                    ],
                    "causal_factor": "true",
                    "causal_impact": "positive",
                    "affected_by_time_series": "true",
                    "ts_effect_direction": "positive"
                }
            },
            {
                "time": "2018-11-08",
                "original_text": "American Water Works (AWK) Ex-Dividend Date Scheduled for November 08, 2018",
                "features": {
                    "keywords": [
                        "AWK",
                        "Ex-Dividend",
                        "Scheduled"
                    ],
                    "sentiment_score": 0.5,
                    "policy_related": "false",
                    "investment_strategy": "true",
                    "sector_focus": [
                        "utilities",
                        "water"
                    ],
                    "causal_factor": "true",
                    "causal_impact": "positive",
                    "affected_by_time_series": "true",
                    "ts_effect_direction": "positive"
                }
            },
            {
                "time": "",
                "original_text": "American States Water (AWR) Q3 Earnings Top, Revenues Lag",
                "features": {
                    "keywords": [
                        "AWR",
                        "Q3",
                        "Earnings",
                        "Top",
                        "Revenues",
                        "Lag"
                    ],
                    "sentiment_score": -0.3,
                    "policy_related": "false",
                    "investment_strategy": "false",
                    "sector_focus": [
                        "utilities",
                        "water"
                    ],
                    "causal_factor": "true",
                    "causal_impact": "negative",
                    "affected_by_time_series": "true",
                    "ts_effect_direction": "negative"
                }
            }
        ]
    ]
}