{
    "2019-09-23": [
        [
            {
                "time": "2018-01-02",
                "original_text": "3M LOSS NOTICE: ROSEN, A LEADING LAW FIRM, Reminds 3M Company Investors of Important September 27th Deadline in Securities Class Action Lawsuit – MMM",
                "features": {
                    "keywords": [
                        "class action",
                        "lawsuit",
                        "investors",
                        "deadline"
                    ],
                    "sentiment_score": -0.6,
                    "policy_related": "false",
                    "investment_strategy": "true",
                    "sector_focus": [
                        "finance",
                        "legal"
                    ],
                    "causal_factor": "true",
                    "causal_impact": "negative",
                    "affected_by_time_series": "false",
                    "ts_effect_direction": "neutral"
                }
            },
            {
                "time": "2018-01-02",
                "original_text": "CLASS ACTION UPDATE for MMM, KPTI and IFF: Levi & Korsinsky, LLP Reminds Investors of Class Actions on Behalf of Shareholders",
                "features": {
                    "keywords": [
                        "class action",
                        "shareholders",
                        "update"
                    ],
                    "sentiment_score": -0.5,
                    "policy_related": "false",
                    "investment_strategy": "true",
                    "sector_focus": [
                        "finance",
                        "legal"
                    ],
                    "causal_factor": "true",
                    "causal_impact": "negative",
                    "affected_by_time_series": "false",
                    "ts_effect_direction": "neutral"
                }
            },
            {
                "time": "2018-01-02",
                "original_text": "Glancy Prongay & Murray Reminds Investors of Looming Deadline in the Class Action Lawsuit Against 3M Company",
                "features": {
                    "keywords": [
                        "class action",
                        "lawsuit",
                        "deadline"
                    ],
                    "sentiment_score": -0.4,
                    "policy_related": "false",
                    "investment_strategy": "true",
                    "sector_focus": [
                        "finance",
                        "legal"
                    ],
                    "causal_factor": "true",
                    "causal_impact": "negative",
                    "affected_by_time_series": "false",
                    "ts_effect_direction": "neutral"
                }
            },
            {
                "time": "2018-01-02",
                "original_text": "UPCOMING DEADLINE ALERT - 3M Company (MMM) - Bronstein, Gewirtz & Grossman, LLC Reminds of Class Action and Lead Plaintiff Deadline: September 27, 2019",
                "features": {
                    "keywords": [
                        "class action",
                        "deadline",
                        "lead plaintiff"
                    ],
                    "sentiment_score": -0.5,
                    "policy_related": "false",
                    "investment_strategy": "true",
                    "sector_focus": [
                        "finance",
                        "legal"
                    ],
                    "causal_factor": "true",
                    "causal_impact": "negative",
                    "affected_by_time_series": "false",
                    "ts_effect_direction": "neutral"
                }
            },
            {
                "time": "2018-01-02",
                "original_text": "SHAREHOLDER ALERT: Pomerantz Law Firm Reminds Shareholders with Losses on their Investment in 3M Company of Class Action Lawsuit and Upcoming Deadline – MMM",
                "features": {
                    "keywords": [
                        "class action",
                        "lawsuit",
                        "shareholders",
                        "losses"
                    ],
                    "sentiment_score": -0.7,
                    "policy_related": "false",
                    "investment_strategy": "true",
                    "sector_focus": [
                        "finance",
                        "legal"
                    ],
                    "causal_factor": "true",
                    "causal_impact": "negative",
                    "affected_by_time_series": "false",
                    "ts_effect_direction": "neutral"
                }
            },
            {
                "time": "2018-01-02",
                "original_text": "3M Adds Assembly Solution Collaborators to Its Expanded Beam Optical Connector Ecosystem",
                "features": {
                    "keywords": [
                        "assembly solution",
                        "collaborators",
                        "optical connector"
                    ],
                    "sentiment_score": 0.6,
                    "policy_related": "false",
                    "investment_strategy": "false",
                    "sector_focus": [
                        "technology",
                        "manufacturing"
                    ],
                    "causal_factor": "true",
                    "causal_impact": "positive",
                    "affected_by_time_series": "false",
                    "ts_effect_direction": "neutral"
                }
            },
            {
                "time": "2018-01-02",
                "original_text": "3M's new Northeast Austin campus opens",
                "features": {
                    "keywords": [
                        "new campus",
                        "Austin"
                    ],
                    "sentiment_score": 0.8,
                    "policy_related": "false",
                    "investment_strategy": "false",
                    "sector_focus": [
                        "real estate",
                        "corporate expansion"
                    ],
                    "causal_factor": "true",
                    "causal_impact": "positive",
                    "affected_by_time_series": "false",
                    "ts_effect_direction": "neutral"
                }
            },
            {
                "time": "2018-01-02",
                "original_text": "3M and Clean Air Asia Act on Climate Change with New Air Pollution Initiative",
                "features": {
                    "keywords": [
                        "climate change",
                        "air pollution",
                        "initiative"
                    ],
                    "sentiment_score": 0.7,
                    "policy_related": "true",
                    "investment_strategy": "false",
                    "sector_focus": [
                        "environmental",
                        "sustainability"
                    ],
                    "causal_factor": "true",
                    "causal_impact": "positive",
                    "affected_by_time_series": "false",
                    "ts_effect_direction": "neutral"
                }
            }
        ]
    ]
}