{
    "2021-11-17": [
        [
            {
                "time": "2023-10-17",
                "original_text": "Vale Courts Latin Steel Mills Again as China Infatuation Fades",
                "features": {
                    "keywords": [
                        "Vale",
                        "Courts",
                        "Latin Steel Mills",
                        "China",
                        "Infatuation Fades"
                    ],
                    "sentiment_score": -0.4,
                    "policy_related": "false",
                    "investment_strategy": "true",
                    "sector_focus": [
                        "steel",
                        "mining"
                    ],
                    "causal_factor": "true",
                    "causal_impact": "negative",
                    "affected_by_time_series": "true",
                    "ts_effect_direction": "negative"
                }
            }
        ]
    ]
}