{
    "2020-02-04": [
        [
            {
                "time": "2023-10-25",
                "original_text": "Thermo Fisher Scientific Inc. Just Reported Full-Year Earnings: Have Analysts Changed Their Mind On The Stock?",
                "features": {
                    "keywords": [
                        "Thermo Fisher Scientific",
                        "full-year earnings",
                        "analysts",
                        "stock"
                    ],
                    "sentiment_score": 0.6,
                    "policy_related": "false",
                    "investment_strategy": "true",
                    "sector_focus": [
                        "healthcare",
                        "biotech"
                    ],
                    "causal_factor": "true",
                    "causal_impact": "positive",
                    "affected_by_time_series": "true",
                    "ts_effect_direction": "positive"
                }
            }
        ]
    ]
}