{
    "2020-01-09": [
        [
            {
                "time": "",
                "original_text": "看这个成绩单，房企没那么难？| 2019年度榜单⑥",
                "features": {
                    "keywords": [
                        "成绩单",
                        "房企",
                        "2019年度榜单"
                    ],
                    "sentiment_score": 0.6,
                    "policy_related": "false",
                    "investment_strategy": "false",
                    "sector_focus": [
                        "房地产"
                    ],
                    "causal_factor": "true",
                    "causal_impact": "positive",
                    "affected_by_time_series": "true",
                    "ts_effect_direction": "positive"
                }
            },
            {
                "time": "",
                "original_text": "绿地控股张玉良：考虑多业务板块分拆上市",
                "features": {
                    "keywords": [
                        "绿地控股",
                        "张玉良",
                        "多业务板块",
                        "分拆上市"
                    ],
                    "sentiment_score": 0.75,
                    "policy_related": "false",
                    "investment_strategy": "true",
                    "sector_focus": [
                        "房地产",
                        "多元化业务"
                    ],
                    "causal_factor": "true",
                    "causal_impact": "positive",
                    "affected_by_time_series": "true",
                    "ts_effect_direction": "positive"
                }
            }
        ]
    ]
}