{
    "2020-08-29": [
        [
            {
                "time": "2023-10-07",
                "original_text": "华为鸿蒙2.0即将亮相，受益股名单曝光",
                "features": {
                    "keywords": [
                        "华为",
                        "鸿蒙",
                        "2.0",
                        "即将亮相",
                        "受益股",
                        "名单曝光"
                    ],
                    "sentiment_score": 0.9,
                    "policy_related": "false",
                    "investment_strategy": "true",
                    "sector_focus": [
                        "科技",
                        "软件"
                    ],
                    "causal_factor": "true",
                    "causal_impact": "positive",
                    "affected_by_time_series": "true",
                    "ts_effect_direction": "positive"
                }
            }
        ]
    ]
}