{
    "2021-12-02": [
        [
            {
                "time": "2023-10-15",
                "original_text": "成都银行：渤海基金减持计划实施完毕",
                "features": {
                    "keywords": [
                        "成都银行",
                        "渤海基金",
                        "减持",
                        "计划实施完毕"
                    ],
                    "sentiment_score": -0.7,
                    "policy_related": "false",
                    "investment_strategy": "true",
                    "sector_focus": [
                        "金融"
                    ],
                    "causal_factor": "true",
                    "causal_impact": "negative",
                    "affected_by_time_series": "true",
                    "ts_effect_direction": "negative"
                }
            },
            {
                "time": "2023-10-15",
                "original_text": "成都银行(601838.SH)股东渤海基金累计减持3612.25万股 减持时间届满 减持股份",
                "features": {
                    "keywords": [
                        "成都银行",
                        "渤海基金",
                        "减持",
                        "3612.25万股",
                        "减持时间届满"
                    ],
                    "sentiment_score": -0.6,
                    "policy_related": "false",
                    "investment_strategy": "true",
                    "sector_focus": [
                        "金融"
                    ],
                    "causal_factor": "true",
                    "causal_impact": "negative",
                    "affected_by_time_series": "true",
                    "ts_effect_direction": "negative"
                }
            },
            {
                "time": "2023-10-15",
                "original_text": "成都银行(601838.SH)：渤海基金已减持3612.2469万股 减持股份",
                "features": {
                    "keywords": [
                        "成都银行",
                        "渤海基金",
                        "减持",
                        "3612.2469万股"
                    ],
                    "sentiment_score": -0.6,
                    "policy_related": "false",
                    "investment_strategy": "true",
                    "sector_focus": [
                        "金融"
                    ],
                    "causal_factor": "true",
                    "causal_impact": "negative",
                    "affected_by_time_series": "true",
                    "ts_effect_direction": "negative"
                }
            },
            {
                "time": "2023-10-15",
                "original_text": "成都银行：渤海基金累计减持1%股份，完成减持计划 拟减持股份",
                "features": {
                    "keywords": [
                        "成都银行",
                        "渤海基金",
                        "减持",
                        "1%股份",
                        "完成减持计划"
                    ],
                    "sentiment_score": -0.7,
                    "policy_related": "false",
                    "investment_strategy": "true",
                    "sector_focus": [
                        "金融"
                    ],
                    "causal_factor": "true",
                    "causal_impact": "negative",
                    "affected_by_time_series": "true",
                    "ts_effect_direction": "negative"
                }
            }
        ]
    ]
}