{
    "2021-10-30": [
        [
            {
                "time": "",
                "original_text": "前10月最高涨幅超104%！这类基金又霸屏，能追高吗？",
                "features": {
                    "keywords": [
                        "前10月",
                        "最高涨幅",
                        "基金",
                        "霸屏",
                        "追高"
                    ],
                    "sentiment_score": 0.7,
                    "policy_related": "false",
                    "investment_strategy": "true",
                    "sector_focus": [
                        "基金"
                    ],
                    "causal_factor": "true",
                    "causal_impact": "positive",
                    "affected_by_time_series": "true",
                    "ts_effect_direction": "positive"
                }
            },
            {
                "time": "",
                "original_text": "中信建投公布11月金股名单，共有23只股票",
                "features": {
                    "keywords": [
                        "中信建投",
                        "11月",
                        "金股名单",
                        "23只股票"
                    ],
                    "sentiment_score": 0.6,
                    "policy_related": "false",
                    "investment_strategy": "true",
                    "sector_focus": [
                        "券商推荐"
                    ],
                    "causal_factor": "true",
                    "causal_impact": "positive",
                    "affected_by_time_series": "true",
                    "ts_effect_direction": "positive"
                }
            },
            {
                "time": "",
                "original_text": "晶澳科技近乎涨停！三季报显示：营收大涨70%",
                "features": {
                    "keywords": [
                        "晶澳科技",
                        "涨停",
                        "三季报",
                        "营收",
                        "大涨70%"
                    ],
                    "sentiment_score": 0.9,
                    "policy_related": "false",
                    "investment_strategy": "false",
                    "sector_focus": [
                        "光伏"
                    ],
                    "causal_factor": "true",
                    "causal_impact": "positive",
                    "affected_by_time_series": "true",
                    "ts_effect_direction": "positive"
                }
            }
        ]
    ]
}