{
    "2020-06-27": [
        [
            {
                "time": "2020-04-15",
                "original_text": "Home improvement projects are underway during COVID-19 with millennials spending the most, says Bank of America",
                "features": {
                    "keywords": [
                        "home improvement",
                        "COVID-19",
                        "millennials",
                        "spending"
                    ],
                    "sentiment_score": 0.7,
                    "policy_related": "false",
                    "investment_strategy": "false",
                    "sector_focus": [
                        "retail",
                        "construction"
                    ],
                    "causal_factor": "true",
                    "causal_impact": "positive",
                    "affected_by_time_series": "true",
                    "ts_effect_direction": "positive"
                }
            },
            {
                "time": "2020-06-20",
                "original_text": "How Lowe’s CEO Remodeled the Company to Benefit Customers and Shareholders",
                "features": {
                    "keywords": [
                        "Lowe's",
                        "CEO",
                        "remodeled",
                        "customers",
                        "shareholders"
                    ],
                    "sentiment_score": 0.85,
                    "policy_related": "false",
                    "investment_strategy": "true",
                    "sector_focus": [
                        "retail",
                        "home improvement"
                    ],
                    "causal_factor": "true",
                    "causal_impact": "positive",
                    "affected_by_time_series": "true",
                    "ts_effect_direction": "positive"
                }
            }
        ]
    ]
}