{
    "2019-12-20": [
        [
            {
                "time": "2019-12-19",
                "original_text": "五粮液（000858）2019年收入超500亿元，改革红利逐步释放",
                "features": {
                    "keywords": [
                        "五粮液",
                        "收入",
                        "改革红利",
                        "500亿元"
                    ],
                    "sentiment_score": 0.9,
                    "policy_related": "false",
                    "investment_strategy": "true",
                    "sector_focus": [
                        "白酒"
                    ],
                    "causal_factor": "true",
                    "causal_impact": "positive",
                    "affected_by_time_series": "true",
                    "ts_effect_direction": "positive"
                }
            },
            {
                "time": "2019-12-19",
                "original_text": "川证券：五粮液2019年收入超500亿元 维持“增持”评级",
                "features": {
                    "keywords": [
                        "五粮液",
                        "收入",
                        "增持",
                        "500亿元"
                    ],
                    "sentiment_score": 0.85,
                    "policy_related": "false",
                    "investment_strategy": "true",
                    "sector_focus": [
                        "白酒"
                    ],
                    "causal_factor": "true",
                    "causal_impact": "positive",
                    "affected_by_time_series": "true",
                    "ts_effect_direction": "positive"
                }
            },
            {
                "time": "2020-01-01",
                "original_text": "预计实现500亿元营收目标 五粮液持续发力数字化转型",
                "features": {
                    "keywords": [
                        "五粮液",
                        "数字化转型",
                        "500亿元"
                    ],
                    "sentiment_score": 0.8,
                    "policy_related": "false",
                    "investment_strategy": "false",
                    "sector_focus": [
                        "白酒"
                    ],
                    "causal_factor": "true",
                    "causal_impact": "positive",
                    "affected_by_time_series": "true",
                    "ts_effect_direction": "positive"
                }
            },
            {
                "time": "2019-12-31",
                "original_text": "北向资金今日净流入37.16亿元，美的集团净买入逾3亿元",
                "features": {
                    "keywords": [
                        "北向资金",
                        "净流入",
                        "美的集团"
                    ],
                    "sentiment_score": 0.7,
                    "policy_related": "false",
                    "investment_strategy": "true",
                    "sector_focus": [
                        "家电"
                    ],
                    "causal_factor": "true",
                    "causal_impact": "positive",
                    "affected_by_time_series": "true",
                    "ts_effect_direction": "positive"
                }
            },
            {
                "time": "2019-12-19",
                "original_text": "高端白酒涨价背后的那点小心思",
                "features": {
                    "keywords": [
                        "高端白酒",
                        "涨价"
                    ],
                    "sentiment_score": 0.6,
                    "policy_related": "false",
                    "investment_strategy": "false",
                    "sector_focus": [
                        "白酒"
                    ],
                    "causal_factor": "true",
                    "causal_impact": "positive",
                    "affected_by_time_series": "true",
                    "ts_effect_direction": "positive"
                }
            },
            {
                "time": "2019-12-19",
                "original_text": "白酒板块市值蒸发338亿 机构:正常波动 看好中长期机会 连续下跌",
                "features": {
                    "keywords": [
                        "白酒板块",
                        "市值蒸发",
                        "正常波动",
                        "中长期机会"
                    ],
                    "sentiment_score": -0.4,
                    "policy_related": "false",
                    "investment_strategy": "true",
                    "sector_focus": [
                        "白酒"
                    ],
                    "causal_factor": "true",
                    "causal_impact": "negative",
                    "affected_by_time_series": "true",
                    "ts_effect_direction": "negative"
                }
            },
            {
                "time": "2020-01-01",
                "original_text": "五粮液重新出发，千亿元营收新起点，再上征程",
                "features": {
                    "keywords": [
                        "五粮液",
                        "千亿元",
                        "营收"
                    ],
                    "sentiment_score": 0.9,
                    "policy_related": "false",
                    "investment_strategy": "false",
                    "sector_focus": [
                        "白酒"
                    ],
                    "causal_factor": "true",
                    "causal_impact": "positive",
                    "affected_by_time_series": "true",
                    "ts_effect_direction": "positive"
                }
            },
            {
                "time": "2019-12-19",
                "original_text": "五粮液茅台互贺跨越千亿 中国白酒开启新世纪",
                "features": {
                    "keywords": [
                        "五粮液",
                        "茅台",
                        "千亿",
                        "白酒"
                    ],
                    "sentiment_score": 0.95,
                    "policy_related": "false",
                    "investment_strategy": "false",
                    "sector_focus": [
                        "白酒"
                    ],
                    "causal_factor": "true",
                    "causal_impact": "positive",
                    "affected_by_time_series": "true",
                    "ts_effect_direction": "positive"
                }
            },
            {
                "time": "2020-01-01",
                "original_text": "李曙光：五粮液跨越千亿成定局 2020年要开展7大工作",
                "features": {
                    "keywords": [
                        "五粮液",
                        "李曙光",
                        "千亿",
                        "7大工作"
                    ],
                    "sentiment_score": 0.85,
                    "policy_related": "false",
                    "investment_strategy": "true",
                    "sector_focus": [
                        "白酒"
                    ],
                    "causal_factor": "true",
                    "causal_impact": "positive",
                    "affected_by_time_series": "true",
                    "ts_effect_direction": "positive"
                }
            }
        ]
    ]
}