{
    "2018-04-09": [
        [
            {
                "time": "",
                "original_text": "看好中国｜消费升级---白马股重回视线 北上资金逐步加仓",
                "features": {
                    "keywords": [
                        "消费升级",
                        "白马股",
                        "北上资金",
                        "加仓"
                    ],
                    "sentiment_score": 0.75,
                    "policy_related": "false",
                    "investment_strategy": "true",
                    "sector_focus": [
                        "消费",
                        "金融"
                    ],
                    "causal_factor": "true",
                    "causal_impact": "positive",
                    "affected_by_time_series": "true",
                    "ts_effect_direction": "positive"
                }
            }
        ]
    ]
}