{
    "2018-03-21": [
        [
            {
                "time": "2018-03-22",
                "original_text": "Randgold Resources Limited (GOLD) Ex-Dividend Date Scheduled for March 22, 2018",
                "features": {
                    "keywords": [
                        "Randgold Resources",
                        "Ex-Dividend",
                        "March 22, 2018"
                    ],
                    "sentiment_score": 0.6,
                    "policy_related": "false",
                    "investment_strategy": "true",
                    "sector_focus": [
                        "mining",
                        "resources"
                    ],
                    "causal_factor": "true",
                    "causal_impact": "positive",
                    "affected_by_time_series": "true",
                    "ts_effect_direction": "positive"
                }
            },
            {
                "time": "2018-03-22",
                "original_text": "AngloGold Ashanti Limited (AU) Ex-Dividend Date Scheduled for March 22, 2018",
                "features": {
                    "keywords": [
                        "AngloGold Ashanti",
                        "Ex-Dividend",
                        "March 22, 2018"
                    ],
                    "sentiment_score": 0.6,
                    "policy_related": "false",
                    "investment_strategy": "true",
                    "sector_focus": [
                        "mining",
                        "resources"
                    ],
                    "causal_factor": "true",
                    "causal_impact": "positive",
                    "affected_by_time_series": "true",
                    "ts_effect_direction": "positive"
                }
            },
            {
                "time": "",
                "original_text": "Is Teck Resources Ltd a Buy?",
                "features": {
                    "keywords": [
                        "Teck Resources Ltd",
                        "Buy"
                    ],
                    "sentiment_score": 0.5,
                    "policy_related": "false",
                    "investment_strategy": "true",
                    "sector_focus": [
                        "mining",
                        "resources"
                    ],
                    "causal_factor": "false",
                    "causal_impact": "neutral",
                    "affected_by_time_series": "true",
                    "ts_effect_direction": "neutral"
                }
            },
            {
                "time": "",
                "original_text": "2 Top Nickel Stocks to Consider Buying Now",
                "features": {
                    "keywords": [
                        "Nickel Stocks",
                        "Buying Now"
                    ],
                    "sentiment_score": 0.7,
                    "policy_related": "false",
                    "investment_strategy": "true",
                    "sector_focus": [
                        "mining",
                        "nickel"
                    ],
                    "causal_factor": "false",
                    "causal_impact": "neutral",
                    "affected_by_time_series": "true",
                    "ts_effect_direction": "neutral"
                }
            }
        ]
    ]
}