{
    "2020-09-14": [
        [
            {
                "time": "2020-09-14",
                "original_text": "1500亿“医药茅台”突然跌停，两机构席位卖出3.13亿元！发生了什么？公司最新回复来了",
                "features": {
                    "keywords": [
                        "医药茅台",
                        "跌停",
                        "机构席位",
                        "卖出"
                    ],
                    "sentiment_score": -0.7,
                    "policy_related": "false",
                    "investment_strategy": "true",
                    "sector_focus": [
                        "医药"
                    ],
                    "causal_factor": "true",
                    "causal_impact": "negative",
                    "affected_by_time_series": "true",
                    "ts_effect_direction": "negative"
                }
            },
            {
                "time": "2020-09-14",
                "original_text": "贵州茅台现4笔大宗交易 共成交4,634.08万元",
                "features": {
                    "keywords": [
                        "贵州茅台",
                        "大宗交易",
                        "成交"
                    ],
                    "sentiment_score": 0.2,
                    "policy_related": "false",
                    "investment_strategy": "false",
                    "sector_focus": [
                        "白酒"
                    ],
                    "causal_factor": "false",
                    "causal_impact": "neutral",
                    "affected_by_time_series": "true",
                    "ts_effect_direction": "neutral"
                }
            },
            {
                "time": "2020-09-15",
                "original_text": "北向资金净流出逾31亿元，外资减仓白酒回流疫苗龙头",
                "features": {
                    "keywords": [
                        "北向资金",
                        "净流出",
                        "白酒",
                        "疫苗"
                    ],
                    "sentiment_score": -0.6,
                    "policy_related": "false",
                    "investment_strategy": "true",
                    "sector_focus": [
                        "白酒",
                        "疫苗"
                    ],
                    "causal_factor": "true",
                    "causal_impact": "negative",
                    "affected_by_time_series": "true",
                    "ts_effect_direction": "negative"
                }
            },
            {
                "time": "2020-09-14",
                "original_text": "消费产业周报：本周消费继续调整 但预计下行空间已有限",
                "features": {
                    "keywords": [
                        "消费产业",
                        "调整",
                        "下行空间"
                    ],
                    "sentiment_score": -0.3,
                    "policy_related": "false",
                    "investment_strategy": "true",
                    "sector_focus": [
                        "消费"
                    ],
                    "causal_factor": "true",
                    "causal_impact": "negative",
                    "affected_by_time_series": "true",
                    "ts_effect_direction": "negative"
                }
            },
            {
                "time": "2020-09-14",
                "original_text": "助力扶贫攻坚 国美携手茅台酱香酒集团再行动",
                "features": {
                    "keywords": [
                        "扶贫攻坚",
                        "国美",
                        "茅台酱香酒"
                    ],
                    "sentiment_score": 0.8,
                    "policy_related": "true",
                    "investment_strategy": "false",
                    "sector_focus": [
                        "白酒",
                        "扶贫"
                    ],
                    "causal_factor": "true",
                    "causal_impact": "positive",
                    "affected_by_time_series": "false",
                    "ts_effect_direction": "neutral"
                }
            },
            {
                "time": "2020-09-14",
                "original_text": "巨丰微策略：发生了什么？北方股王突然跌停 融资客连续7日减仓 调整尚未见底？",
                "features": {
                    "keywords": [
                        "北方股王",
                        "跌停",
                        "融资客",
                        "减仓"
                    ],
                    "sentiment_score": -0.8,
                    "policy_related": "false",
                    "investment_strategy": "true",
                    "sector_focus": [
                        "综合"
                    ],
                    "causal_factor": "true",
                    "causal_impact": "negative",
                    "affected_by_time_series": "true",
                    "ts_effect_direction": "negative"
                }
            },
            {
                "time": "2020-09-14",
                "original_text": "16股获买入评级 最新:贵州茅台",
                "features": {
                    "keywords": [
                        "买入评级",
                        "贵州茅台"
                    ],
                    "sentiment_score": 0.7,
                    "policy_related": "false",
                    "investment_strategy": "true",
                    "sector_focus": [
                        "白酒"
                    ],
                    "causal_factor": "true",
                    "causal_impact": "positive",
                    "affected_by_time_series": "false",
                    "ts_effect_direction": "neutral"
                }
            },
            {
                "time": "2020-09-14",
                "original_text": "食品饮料行业周报：旺销可期 积极布局",
                "features": {
                    "keywords": [
                        "食品饮料",
                        "旺销",
                        "布局"
                    ],
                    "sentiment_score": 0.6,
                    "policy_related": "false",
                    "investment_strategy": "true",
                    "sector_focus": [
                        "食品饮料"
                    ],
                    "causal_factor": "true",
                    "causal_impact": "positive",
                    "affected_by_time_series": "false",
                    "ts_effect_direction": "neutral"
                }
            },
            {
                "time": "2020-09-14",
                "original_text": "第三代半导体强势上冲 茅台再次受到市场资金集中关注",
                "features": {
                    "keywords": [
                        "第三代半导体",
                        "茅台",
                        "市场资金"
                    ],
                    "sentiment_score": 0.5,
                    "policy_related": "false",
                    "investment_strategy": "true",
                    "sector_focus": [
                        "半导体",
                        "白酒"
                    ],
                    "causal_factor": "true",
                    "causal_impact": "positive",
                    "affected_by_time_series": "true",
                    "ts_effect_direction": "positive"
                }
            }
        ]
    ]
}