{
    "2020-06-06": [
        [
            {
                "time": "",
                "original_text": "【太平洋通信李宏涛团队】华为半年报业绩亮眼，“侧翼协同”公司价值提升",
                "features": {
                    "keywords": [
                        "华为",
                        "半年报",
                        "业绩亮眼",
                        "侧翼协同",
                        "公司价值提升"
                    ],
                    "sentiment_score": 0.9,
                    "policy_related": "false",
                    "investment_strategy": "true",
                    "sector_focus": [
                        "科技",
                        "通信"
                    ],
                    "causal_factor": "true",
                    "causal_impact": "positive",
                    "affected_by_time_series": "true",
                    "ts_effect_direction": "positive"
                }
            }
        ]
    ]
}