{
    "2020-07-07": [
        [
            {
                "time": "",
                "original_text": "6家上市公司预告上半年业绩 28.80%报喜",
                "features": {
                    "keywords": [
                        "上市公司",
                        "业绩",
                        "预告",
                        "报喜"
                    ],
                    "sentiment_score": 0.75,
                    "policy_related": "false",
                    "investment_strategy": "true",
                    "sector_focus": [
                        "综合"
                    ],
                    "causal_factor": "true",
                    "causal_impact": "positive",
                    "affected_by_time_series": "true",
                    "ts_effect_direction": "positive"
                }
            },
            {
                "time": "",
                "original_text": "军工行业周报：市场交易情绪升温 关注军工优质低估值品种修复行情",
                "features": {
                    "keywords": [
                        "军工",
                        "行业",
                        "周报",
                        "交易情绪",
                        "升温",
                        "低估值",
                        "修复行情"
                    ],
                    "sentiment_score": 0.8,
                    "policy_related": "false",
                    "investment_strategy": "true",
                    "sector_focus": [
                        "军工"
                    ],
                    "causal_factor": "true",
                    "causal_impact": "positive",
                    "affected_by_time_series": "true",
                    "ts_effect_direction": "positive"
                }
            }
        ]
    ]
}