{
    "2020-07-22": [
        [
            {
                "time": "2023-10-01",
                "original_text": "Brokers Are Upgrading Their Views On Morgan Stanley (NYSE:MS) With These New Forecasts",
                "features": {
                    "keywords": [
                        "Brokers",
                        "Upgrading",
                        "Morgan Stanley",
                        "Forecasts"
                    ],
                    "sentiment_score": 0.75,
                    "policy_related": "false",
                    "investment_strategy": "true",
                    "sector_focus": [
                        "finance"
                    ],
                    "causal_factor": "true",
                    "causal_impact": "positive",
                    "affected_by_time_series": "true",
                    "ts_effect_direction": "positive"
                }
            },
            {
                "time": "2023-10-01",
                "original_text": "Credit Suisse Set to Score a Smaller Role on Ant’s Mega IPO",
                "features": {
                    "keywords": [
                        "Credit Suisse",
                        "Smaller Role",
                        "Ant",
                        "Mega IPO"
                    ],
                    "sentiment_score": -0.4,
                    "policy_related": "false",
                    "investment_strategy": "false",
                    "sector_focus": [
                        "finance",
                        "technology"
                    ],
                    "causal_factor": "true",
                    "causal_impact": "negative",
                    "affected_by_time_series": "true",
                    "ts_effect_direction": "negative"
                }
            }
        ]
    ]
}